artap/__init__.py
artap/algorithm.py
artap/algorithm_NSGAII.py
artap/algorithm_bayesopt.py
artap/algorithm_cem.py
artap/algorithm_cmaes.py
artap/algorithm_genetic.py
artap/algorithm_gradient_descent.py
artap/algorithm_monte_carlo.py
artap/algorithm_nlopt.py
artap/algorithm_pymoo.py
artap/algorithm_scipy.py
artap/algorithm_sensitivity.py
artap/algorithm_swarm.py
artap/algorithm_sweep.py
artap/archive.py
artap/benchmark_functions.py
artap/benchmark_pareto.py
artap/benchmark_robust.py
artap/colormaps.py
artap/config.py
artap/datastore.py
artap/doe.py
artap/executor.py
artap/individual.py
artap/job.py
artap/operators.py
artap/problem.py
artap/quality_indicator.py
artap/reliability_analysis.py
artap/results.py
artap/surrogate.py
artap/surrogate_scikit.py
artap/surrogate_smt.py
artap/utils.py
artap/tests/__init__.py
artap/tests/_test_scikit.py
artap/tests/test_agros.py
artap/tests/test_algorithm.py
artap/tests/test_archive.py
artap/tests/test_benchmark_pareto.py
artap/tests/test_benchmark_robust.py
artap/tests/test_benchmarks.py
artap/tests/test_calculation_fails.py
artap/tests/test_datastore.py
artap/tests/test_generators.py
artap/tests/test_gradients.py
artap/tests/test_job.py
artap/tests/test_local_comsol.py
artap/tests/test_local_cst.py
artap/tests/test_operators.py
artap/tests/test_problem_bayesopt.py
artap/tests/test_problem_cem.py
artap/tests/test_problem_cmaes.py
artap/tests/test_problem_epsmoea.py
artap/tests/test_problem_gradient_descent.py
artap/tests/test_problem_monte_carlo.py
artap/tests/test_problem_nlopt.py
artap/tests/test_problem_nsga2.py
artap/tests/test_problem_pymoo.py
artap/tests/test_problem_scipy.py
artap/tests/test_problem_swarm.py
artap/tests/test_quality_indicator.py
artap/tests/test_reliability_analysis.py
artap/tests/test_remote_condor.py
artap/tests/test_results.py
artap/tests/test_robust.py
artap/tests/test_sensitivity.py
artap/tests/test_surrogate_eval.py
artap/tests/test_surrogate_function.py
artap/tests/test_surrogate_scikit.py
artap-2024.2.19.3045.dist-info/LICENSE
artap-2024.2.19.3045.dist-info/METADATA
artap-2024.2.19.3045.dist-info/WHEEL
artap-2024.2.19.3045.dist-info/top_level.txt
artap-2024.2.19.3045.dist-info/RECORD
