Metadata-Version: 2.1
Name: artap
Version: 2024.2.19.3045
Summary: Platform for robust design optimization
Home-page: http://www.agros2d.org/artap/
Author: Artap Team
Author-email: artap.framework@gmail.com
License: License :: OSI Approved :: MIT License
Classifier: Intended Audience :: Science/Research
Classifier: Operating System :: POSIX :: Linux
Classifier: Topic :: Scientific/Engineering
Classifier: Programming Language :: Python :: 3.6
Classifier: Programming Language :: Python :: 3.7
Classifier: Programming Language :: Python :: 3.8
Classifier: License :: OSI Approved :: MIT License
Classifier: Operating System :: OS Independent
Requires-Python: >=3.6
License-File: LICENSE
Requires-Dist: SALib
Requires-Dist: appdirs
Requires-Dist: cython
Requires-Dist: hypothesis
Requires-Dist: joblib
Requires-Dist: matplotlib
Requires-Dist: nlopt
Requires-Dist: numpy
Requires-Dist: numpy (>=1.13.3)
Requires-Dist: pyDOE2
Requires-Dist: pymoo
Requires-Dist: pytest
Requires-Dist: rpyc
Requires-Dist: scikit-learn
Requires-Dist: scipy
Requires-Dist: setuptools
Requires-Dist: six
Requires-Dist: smt
Requires-Dist: tensorflow
Requires-Dist: wheel
Provides-Extra: full
Requires-Dist: agrossuite (>=0.01) ; extra == 'full'
